{"cameraMode":{"drawMode":0,"name":"Shaded","section":"Shading Mode"},"sceneLighting":true,"audioPlay":false,"sceneViewState":{"m_AlwaysRefresh":false,"showFog":true,"showSkybox":true,"showFlares":true,"showImageEffects":true,"showParticleSystems":true,"showVisualEffectGraphs":true,"m_FxEnabled":true},"in2DMode":false,"pivot":{"x":4.853784561157227,"y":2.065288782119751,"z":7.19759464263916},"rotation":{"x":0.05793284624814987,"y":0.8629328608512878,"z":-0.1016969159245491,"w":0.49156397581100466},"size":4.27098274230957,"orthographic":false}